leet_topic/__init__.py
leet_topic/bokeh_app.py
leet_topic/leet_topic.py
leet_topic-0.0.11.dist-info/METADATA
leet_topic-0.0.11.dist-info/WHEEL
leet_topic-0.0.11.dist-info/top_level.txt
leet_topic-0.0.11.dist-info/RECORD
