Metadata-Version: 2.1
Name: leet-topic
Version: 0.0.11
Summary: A new transformer-based topic modeling library.
Author: WJB Mattingly
Requires-Dist: pandas <2.0.0,>=1.0.0
Requires-Dist: bokeh <2.4.3,>=2.4.0
Requires-Dist: sentence-transformers >=2.0.0
Requires-Dist: umap-learn >=0.5.0
Requires-Dist: hdbscan >=0.8.0
Requires-Dist: wrapt ==1.14.0
Requires-Dist: tensorflow >=2.8.0
Requires-Dist: spacy >=3.3.0
Requires-Dist: gensim >=4.3.0
Requires-Dist: annoy >=1.17.0
